modern_colorthief/__init__.py
modern_colorthief/_modern_colorthief.cpython-314t-aarch64-linux-gnu.so
modern_colorthief/_modern_colorthief.pyi
modern_colorthief/cli.py
modern_colorthief-0.1.11.dist-info/METADATA
modern_colorthief-0.1.11.dist-info/WHEEL
modern_colorthief-0.1.11.dist-info/entry_points.txt
modern_colorthief-0.1.11.dist-info/licenses/LICENSE
modern_colorthief-0.1.11.dist-info/RECORD
