Metadata-Version: 2.4
Name: modern_colorthief
Version: 0.1.11
Classifier: Programming Language :: Rust
Classifier: Programming Language :: Python :: Implementation :: CPython
Classifier: Programming Language :: Python :: Implementation :: PyPy
License-File: LICENSE
Author-email: baseplate-admin <61817579+baseplate-admin@users.noreply.github.com>
Requires-Python: >3.9
Project-URL: documentation, https://modern-colorthief.readthedocs.io
Project-URL: homepage, https://github.com/baseplate-admin/modern_colorthief
Project-URL: repository, https://github.com/baseplate-admin/modern_colorthief
